source/__init__.py
source/module_print.py
conflict_yaroslav2131234-0.1.0.dist-info/METADATA
conflict_yaroslav2131234-0.1.0.dist-info/WHEEL
conflict_yaroslav2131234-0.1.0.dist-info/top_level.txt
conflict_yaroslav2131234-0.1.0.dist-info/RECORD
